{

    "vrais mots": [
        {"anglais": "ASLR", "francais": "Disposition Stochastique de l'espace d'addressage", "genre": "m"},
        {"anglais": "BBS (Bulletin Board System)", "francais": "Babillard électronique", "genre": "m"},
        {"anglais": "BYOD (Bring Your Own Device)", "francais": "AVEC (Apportez Votre Equipement personnel de Communication)"},
        {"anglais": "CDROM", "francais": "Cédérom", "genre": "m"},
        {"anglais": "Cascading Style Sheets (CSS)", "francais": "Feuilles de style en cascade", "genre": "f"},
        {"anglais": "Computer Science (CS)", "francais": "Science informatique", "genre": "f"},
        {"anglais": "FPGA (Field-Programmable Gate Array)", "francais": "CIPP (Circuit Intégré Prédiffusé Programmable)", "genre": "m"},
        {"anglais": "GC", "francais": "Ramasse-miettes, glaneur de cellule", "genre": "m"},
        {"anglais": "ROM (Read-Only Memory)", "francais": "Mémoire morte", "genre": "f"},
        {"anglais": "SoC (System-on-Chip)", "francais": "Puce-système", "genre": "f"},
        {"anglais": "TL;DR (Too Long; Didn't Read)" , "francais": "TL;PL (Trop Long; Pas Lu)"},
        {"anglais": "URL", "francais": "Adresse réticulaire", "genre": "f"},
        {"anglais": "USB key", "francais": "Mémorette", "genre": "f"},
        {"anglais": "Web cache", "francais": "Cache-toile", "genre": "m"},
        {"anglais": "Web", "francais": "Toile", "genre": "f"},
        {"anglais": "XSS (Cross Site Scripting)", "francais": "ICID (Injection de Code Indirect à Distance)", "genre": "f"},
        {"anglais": "Ampersand", "francais": "Esperluette", "genre": "f"},
        {"anglais": "Angle brackets", "francais": "Chevrons", "genre": "m"},
        {"anglais": "Anti-pattern", "francais": "Anti-patron", "genre": "m"},
        {"anglais": "Applet", "francais": "Appliquette", "genre": "f"},
        {"anglais": "Back office", "francais": "Arrière-guichet", "genre": "m"},
        {"anglais": "Back-end services", "francais": "Services dorsaux", "genre": "m"},
        {"anglais": "Backdoor", "francais": "Porte dérobée", "genre": "f"},
        {"anglais": "Backport", "francais": "Rétroportage", "genre": "m"},
        {"anglais": "Backslash", "francais": "Barre oblique inversée", "genre": "f"},
        {"anglais": "Benchmark", "francais": "Banc d'essai", "genre": "m"},
        {"anglais": "Big data", "francais": "Mégadonnées", "genre": "f"},
        {"anglais": "Big-endian", "francais": "Grand boutien", "genre": "m"},
        {"anglais": "Bloatware", "francais": "Boufficiel", "genre": "m"},
        {"anglais": "Boot", "francais": "Amorçage", "genre": "m"},
        {"anglais": "Browser", "francais": "Navigateur", "genre": "m"},
        {"anglais": "Bug", "francais": "Bogue", "genre": "m"},
        {"anglais": "Byte", "francais": "Octet", "genre": "m"},
        {"anglais": "Cache memory", "francais": "Antémémoire", "genre": "f"},
        {"anglais": "Callback function", "francais": "Fonction de rappel", "genre": "f"},
        {"anglais": "Capitalization", "francais": "Majusculation", "genre": "f"},
        {"anglais": "Checksum", "francais": "Somme de contrôle", "genre": "f"},
        {"anglais": "Chipset", "francais": "Jeu de puces", "genre": "m"},
        {"anglais": "Cloud computing", "francais": "Infonuagique", "genre": "f"},
        {"anglais": "Cluster", "francais": "Grappe", "genre": "f"},
        {"anglais": "Cookie", "francais": "Témoin de connexion", "genre": "m"},
        {"anglais": "Core dump", "francais": "Vidage de mémoire", "genre": "m"},
        {"anglais": "Dangling pointer", "francais": "Pointeur fou", "genre": "m"},
        {"anglais": "Database", "francais": "Base de données", "genre": "f"},
        {"anglais": "Deadlock", "francais": "Étreinte fatale", "genre": "f"},
        {"anglais": "Debugger", "francais": "Dévermineur", "genre": "m"},
        {"anglais": "Desktop", "francais": "Ordinateur de bureau", "genre": "m"},
        {"anglais": "Device", "francais": "Appareil", "genre": "m"},
        {"anglais": "Digital", "francais": "Numérique", "genre": "m"},
        {"anglais": "Double word", "francais": "Trente-deuzet", "genre": "m"},
        {"anglais": "Download", "francais": "Téléchargement", "genre": "m"},
        {"anglais": "E-mail", "francais": "Courriel", "genre": "m"},
        {"anglais": "Endianness", "francais": "Boutisme", "genre": "m"},
        {"anglais": "Firewall", "francais": "Pare-feu", "genre": "m"},
        {"anglais": "Firmware", "francais": "Micrologiciel", "genre": "m"},
        {"anglais": "Flag", "francais": "Fanion", "genre": "m"},
        {"anglais": "Flame", "francais": "Propos incendiaire", "genre": "m"},
        {"anglais": "Flood", "francais": "Matraquage", "genre": "m"},
        {"anglais": "Fork", "francais": "Scission", "genre": "f"},
        {"anglais": "Framework", "francais": "Cadriciel", "genre": "m"},
        {"anglais": "Freeware", "francais": "Gratuiciel", "genre": "m"},
        {"anglais": "Front office", "francais": "Guichet", "genre": "m"},
        {"anglais": "Fuzzer", "francais": "Générateur d'anomalies", "genre": "m"},
        {"anglais": "Fuzzing", "francais": "Frelatage en masse", "genre": "m"},
        {"anglais": "Glue code", "francais": "Code ciment", "genre": "m"},
        {"anglais": "God object", "francais": "Objet omniscient", "genre": "m"},
        {"anglais": "Hacked", "francais": "Intrusé", "genre": "m"},
        {"anglais": "Hacker", "francais": "Fouineur", "genre": "m"},
        {"anglais": "Hash table", "francais": "Tableau à adressage dispersé", "genre": "m"},
        {"anglais": "Hash", "francais": "Condensat", "genre": "m"},
        {"anglais": "Hashtag", "francais": "Mot-croisillon", "genre": "m"},
        {"anglais": "Heap spray", "francais": "Pulvérisation du tas", "genre": "m"},
        {"anglais": "Home row", "francais": "Touche de repos", "genre": "f"},
        {"anglais": "Hub", "francais": "Concentrateur", "genre": "m"},
        {"anglais": "Hyperlink", "francais": "Hyperlien", "genre": "m"},
        {"anglais": "Instruction pipeline", "francais": "Instruoduc", "genre": "m"},
        {"anglais": "Lazy evaluation", "francais": "Évaluation paresseuse", "genre": "f"},
        {"anglais": "Little-endian", "francais": "Petit boutien", "genre": "m"},
        {"anglais": "Lurker", "francais": "Fureteur", "genre": "m"},
        {"anglais": "Malware", "francais": "Maliciel", "genre": "m"},
        {"anglais": "Man-in-the-middle attack", "francais": "Attaque de l'homme du milieu", "genre": "f"},
        {"anglais": "Middleware", "francais": "Intergiciel", "genre": "m"},
        {"anglais": "Monkey-in-the-middle attack", "francais": "Attaque du singe intercepteur", "genre": "f"},
        {"anglais": "Namespace", "francais": "Espace de noms", "genre": "m"},
        {"anglais": "Number sign", "francais": "Croisillon", "genre": "m"},
        {"anglais": "Obfuscation", "francais": "Noircissement de code", "genre": "m"},
        {"anglais": "Online chat", "francais": "Clavardage", "genre": "m"},
        {"anglais": "Overclocking", "francais": "Surcadençage", "genre": "m"},
        {"anglais": "Patch", "francais": "Rustine logicielle", "genre": "f"},
        {"anglais": "Pharming", "francais": "Devoiement", "genre": "m"},
        {"anglais": "Phishing attack", "francais": "Attaque par filoutage", "genre": "f"},
        {"anglais": "Phishing", "francais": "Hameçonnage", "genre": "m"},
        {"anglais": "Pipeline", "francais": "Bitoduc", "genre": "m"},
        {"anglais": "Plugin", "francais": "Greffon", "genre": "m"},
        {"anglais": "Podcasting", "francais": "Balladodiffusion", "genre": "f"},
        {"anglais": "Polling", "francais": "Attente active", "genre": "f"},
        {"anglais": "Program counter", "francais": "Compteur ordinal", "genre": "m"},
        {"anglais": "Proxy", "francais": "Mandataire", "genre": "m"},
        {"anglais": "Refactoring", "francais": "Réusinage", "genre": "m"},
        {"anglais": "Repository", "francais": "Dépôt", "genre": "m"},
        {"anglais": "Return oriented programming", "francais": "Exploitation focalisée sur le retour", "genre": "f"},
        {"anglais": "Reverse proxy", "francais": "Mandataire inverse", "genre": "m"},
        {"anglais": "Reverse-engineering", "francais": "Ingénierie à rebours", "genre": "f"},
        {"anglais": "Rolling release", "francais": "Publication continue", "genre": "f"},
        {"anglais": "Scale", "francais": "Passe à l’échelle"},
        {"anglais": "Scaling", "francais": "Passage à l’échelle", "genre": "m"},
        {"anglais": "Shareware", "francais": "Partagiciel", "genre": "m"},
        {"anglais": "Shell code", "francais": "Code encoquillé", "genre": "m"},
        {"anglais": "Slash", "francais": "Barre oblique", "genre": "f"},
        {"anglais": "Smart grids", "francais": "Grilles malignes", "genre": "f"},
        {"anglais": "Spam", "francais": "Polluriel, pourriel", "genre": "m"},
        {"anglais": "Spammeur", "francais": "Arroseur publicitaire", "genre": "m"},
        {"anglais": "Spinlock", "francais": "Tourniquet", "genre": "m"},
        {"anglais": "Spyware", "francais": "Espiogiciel", "genre": "m"},
        {"anglais": "Stack cookie", "francais": "Biscuit de pile", "genre": "m"},
        {"anglais": "Stack overflow", "francais": "Dépassement de pile", "genre": "m"},
        {"anglais": "Switch", "francais": "Commutateur", "genre": "m"},
        {"anglais": "Tag", "francais": "Étiquette", "genre": "f"},
        {"anglais": "Thumbnail", "francais": "Imagette", "genre": "f"},
        {"anglais": "To deface", "francais": "Défigurer"},
        {"anglais": "To reverse", "francais": "Détricoter"},
        {"anglais": "Tutorial", "francais": "Didacticiel", "genre": "m"},
        {"anglais": "Upload", "francais": "Téléversement", "genre": "m"},
        {"anglais": "Version control system", "francais": "Logiciel de gestion de versions", "genre": "m"},
        {"anglais": "Verbose", "francais": "Volubile"},
        {"anglais": "Watchdog", "francais": "Chien de garde", "genre": "m"},
        {"anglais": "Webcam", "francais": "Cybercaméra", "genre": "f"},
        {"anglais": "Webmaster", "francais": "Webmestre", "genre": "m"},
        {"anglais": "Library", "francais": "Bibliothèque", "genre": "m"}
    ],

    "faux mots": [
        {"anglais": "DRY (Don't Repeat Yourself)", "francais": "NTRP (Ne Te Répète Pas)"},
        {"anglais": "NIH (Not Invented Here)", "francais": "PII (Pas Inventé Ici)"},
        {"anglais": "RTFM (Read The Fucking Manual)", "francais": "LPDM (Lis le Putain De Manuel)"},
        {"anglais": "Branch merging", "francais": "Fusion de branches", "genre": "f"},
        {"anglais": "Buzzword", "francais": "Mot à la mode", "genre": "m"},
        {"anglais": "Commit", "francais": "Atome de code", "genre": "m"},
        {"anglais": "Cryptocoin", "francais": "Cybersou", "genre": "m"},
        {"anglais": "Cryptoparty", "francais": "Chiffrofête", "genre": "f"},
        {"anglais": "Empowerment", "francais": "Empouvoirement", "genre": "m"},
        {"anglais": "Favicon", "francais": "Favorimage", "genre": "f"},
        {"anglais": "Laptop", "francais": "Ordinateur de giron", "genre": "m"},
        {"anglais": "Lolcat", "francais": "Chatmusant", "genre": "m"},
        {"anglais": "Pull-request", "francais": "Fusiodemande", "genre": "f"},
        {"anglais": "Smartphone", "francais": "Malinphone", "genre": "m"},
        {"anglais": "Stand-up meeting", "francais": "Réunion debout", "genre": "f"},
        {"anglais": "To spoil", "francais": "Divulgâcher"},
        {"anglais": "Tweet", "francais": "Gazouillis", "genre": "m"},
        {"anglais": "Walled garden", "francais": "Jardin secret, communauté prison"},
        {"anglais": "Bot", "francais": "Robot", "genre": "m"},
        {"anglais": "TIL (Today I Learnt)", "francais": "AJA (Aujourd'hui J'ai Appris)"}
    ]

}
